{
  "frame": {
    "name": "Based Endorsements",
    "version": "1",
    "iconUrl": "https://oreemo.xyz/icon.png",
    "homeUrl": "https://oreemo.xyz",
    "imageUrl": "https://oreemo.xyz/image.png",
    "buttonTitle": "Endorse Builder",
    "splashImageUrl": "https://oreemo.xyz/splash.png",
    "splashBackgroundColor": "#0052FF",
    "webhookUrl": "https://oreemo.xyz/api/webhook",
    "subtitle": "Verify talent, on Base.",
    "description": "Empower builders! Instantly mint verifiable on-chain attestations via EAS on Base, boosting their Talent Protocol reputation. Connects Basenames for true identity.",
    "primaryCategory": "social",
    "tags": [
      "base",
      "farcaster",
      "onchainkit",
      "builders",
      "reputation"
    ],
    "tagline": "Empower builders on Base! ",
    "ogTitle": "Base Endorsements",
    "ogDescription": "Boost builder reputation on Base! Use Base Endorsements to mint verifiable on-chain attestations.",
    "castShareUrl": "https://oreemo.xyz"
  },
  "accountAssociation": {
    "header": "eyJmaWQiOjE0NDQ3NzQsInR5cGUiOiJjdXN0b2R5Iiwia2V5IjoiMHhGODVDMzEzMTY4NjJmOGU0YjM4N0U3NTViY0ZkYTA2MDMzRDIzOTAwIn0",
    "payload": "eyJkb21haW4iOiJvcmVlbW8ueHl6In0",
    "signature": "HaAbBRCnc4gkkin7B86mCe/6X8NIafoQuPrWwj28EEA5UrL4LEp9rOJyzDC9feuNK1kv/JO23zyr8tH6xCJRvhs="
  }
}